omi/__init__.py
omi/__main__.py
omi/base.py
omi/cli.py
omi/conversion.py
omi/conversions/README.md
omi/conversions/__init__.py
omi/conversions/utils.py
omi/conversions/v152_to_v160.py
omi/conversions/v160_to_v20.py
omi/data/README.md
omi/data/licenses.json
omi/inspection.py
omi/license.py
omi/settings.py
omi/validation.py
omi-1.1.0.dist-info/AUTHORS.rst
omi-1.1.0.dist-info/LICENSE
omi-1.1.0.dist-info/METADATA
omi-1.1.0.dist-info/WHEEL
omi-1.1.0.dist-info/RECORD
