Metadata-Version: 2.3
Name: omi
Version: 1.1.0
Summary: A library to process and translate open energy metadata.
License: AGPL-3.0
Author: Hendrik Huyskens
Author-email: hendrik.huyskens@rl-institut.de
Requires-Python: >=3.9,<3.13
Classifier: License :: OSI Approved :: GNU Affero General Public License v3
Classifier: Programming Language :: Python :: 3
Classifier: Programming Language :: Python :: 3.9
Classifier: Programming Language :: Python :: 3.10
Classifier: Programming Language :: Python :: 3.11
Classifier: Programming Language :: Python :: 3.12
Requires-Dist: click (>=8.1.7,<9.0.0)
Requires-Dist: frictionless (>=5.17.0,<6.0.0)
Requires-Dist: jsonschema (>=4.22.0,<5.0.0)
Requires-Dist: oemetadata (>=1.5.2)
Requires-Dist: pandas (>=2.2.2,<3.0.0)
Requires-Dist: python-dateutil (>=2.9.0,<3.0.0)
Requires-Dist: rdfLib (>=7.0.0,<8.0.0)
